acss_core/__init__.py
acss_core/config.py
acss_core/logger.py
acss_core/service.py
acss_core/simple_service.py
acss_core/topics.py
acss_core/adapter/MsgBusWriter.py
acss_core/adapter/__init__.py
acss_core/adapter/petra/BPMAdapter.py
acss_core/adapter/petra/PetraAdapter.py
acss_core/adapter/petra/PetraMachineAdapter.py
acss_core/adapter/petra/PetraSimDatabase.py
acss_core/adapter/petra/TineAdapter.py
acss_core/adapter/petra/TineSimAdapter.py
acss_core/adapter/petra/__init__.py
acss_core/adapter/petra/bpm_fit.py
acss_core/adapter/petra/simulation_db_types.py
acss_core/adapter/petra/utils.py
acss_core/adapter/petra/config/__init__.py
acss_core/adapter/petra/config/constants.csv
acss_core/adapter/petra/config/bpm_settings/BPMsettings.csv
acss_core/adapter/petra/config/bpm_settings/__init__.py
acss_core/adapter/petra/config/bpm_settings/common/DWOct.par
acss_core/adapter/petra/config/bpm_settings/common/DWRac.par
acss_core/adapter/petra/config/bpm_settings/common/NOOct.par
acss_core/adapter/petra/config/bpm_settings/common/OOArc.par
acss_core/adapter/petra/config/bpm_settings/common/OOStr.par
acss_core/adapter/petra/config/bpm_settings/common/P3XOc.par
acss_core/adapter/petra/config/bpm_settings/common/P3XUd.par
acss_core/adapter/petra/config/bpm_settings/common/UNCtd.par
acss_core/adapter/petra/config/bpm_settings/common/UNEnt.par
acss_core/adapter/petra/config/bpm_settings/common/UNExt.par
acss_core/adapter/petra/config/bpm_settings/common/UNIvu.par
acss_core/adapter/petra/config/bpm_settings/common/__init__.py
acss_core/adapter/petra/config/sim_data/__init__.py
acss_core/adapter/petra/config/sim_data/all-hcor-currents-3-5-22.pickle
acss_core/adapter/petra/config/sim_data/all-hcor-names-3-5-22.pickle
acss_core/adapter/petra/config/sim_data/all-hcor-strengths-3-5-22.pickle
acss_core/adapter/petra/config/sim_data/all-vcor-currents-3-5-22.pickle
acss_core/adapter/petra/config/sim_data/all-vcor-names-3-5-22.pickle
acss_core-0.0.16.dist-info/LICENSE
acss_core-0.0.16.dist-info/METADATA
acss_core-0.0.16.dist-info/WHEEL
acss_core-0.0.16.dist-info/top_level.txt
acss_core-0.0.16.dist-info/RECORD
