Metadata-Version: 2.1
Name: acss-core
Version: 0.0.16
Summary: Pipeline for accelerators
Home-page: https://github.com/desy-ml/acss-core
Author: Michael Boese
Author-email: michael.boese@desy.de
Project-URL: Bug Tracker, https://github.com/desy-ml/acss-core/issues
Classifier: Programming Language :: Python :: 3
Classifier: License :: OSI Approved :: MIT License
Classifier: Operating System :: OS Independent
Requires-Python: >=3.8
License-File: LICENSE
Requires-Dist: confluent-kafka
Requires-Dist: requests
Requires-Dist: pyyaml
Requires-Dist: python-logstash
Requires-Dist: numpy
Requires-Dist: dacite
Requires-Dist: mysql-connector-python
